<?xml version="1.0" encoding="UTF-8"?>
<metadata xml:lang="en"><Esri><CreaDate>20170217</CreaDate><CreaTime>11502600</CreaTime><ArcGISFormat>1.0</ArcGISFormat><ArcGISstyle>FGDC CSDGM Metadata</ArcGISstyle><SyncOnce>TRUE</SyncOnce><DataProperties><itemProps><itemLocation><linkage Sync="TRUE">file://\\KARRAKERLAB2-PC\C$\Users\KarrakerLab\Desktop\2017Anntemp\COLO_Maps_Report\COLO_Shapefiles\Surveyed_Wetlands</linkage><protocol Sync="TRUE">Local Area Network</protocol></itemLocation></itemProps><copyHistory><copy source="C:\Users\KarrakerLab\Desktop\WOODS\GIS\NRS410_BIData\TopoBI\TopoBI\Surveyed_Wetlands" dest="\\KARRAKERLAB2-PC\C$\Users\KarrakerLab\Desktop\2017Anntemp\COLO_Maps_Report\COLO_Shapefiles\Surveyed_Wetlands" date="20170217" time="11502600"></copy></copyHistory></DataProperties></Esri></metadata>
